agnosmodel2/__init__.py
agnosmodel2/agnosmodel2.py
agnosmodel2/plus.py
agnosmodel2-0.0.1a0.dist-info/licenses/LICENSE
agnosmodel2-0.0.1a0.dist-info/METADATA
agnosmodel2-0.0.1a0.dist-info/WHEEL
agnosmodel2-0.0.1a0.dist-info/top_level.txt
agnosmodel2-0.0.1a0.dist-info/RECORD
