Metadata-Version: 2.4
Name: agnosmodel2
Version: 0.0.1a0
Summary: Universal Generative AI provider interface — switch providers without changing code.
Author-email: gauravkg32 <agnosweaver@gmail.com>
License-Expression: PolyForm-Noncommercial-1.0.0
Project-URL: Homepage, https://github.com/agnosweaver/agnosmodel2
Project-URL: Repository, https://github.com/agnosweaver/agnosmodel2
Project-URL: License, https://polyformproject.org/licenses/noncommercial/1.0.0
Keywords: generative-ai,provider,agnostic,ai,agnosweaver
Classifier: Development Status :: 3 - Alpha
Classifier: Intended Audience :: Developers
Classifier: Topic :: Software Development :: Libraries :: Python Modules
Classifier: Programming Language :: Python :: 3
Classifier: Programming Language :: Python :: 3 :: Only
Classifier: Programming Language :: Python :: 3.11
Requires-Python: >=3.11
License-File: LICENSE
Provides-Extra: plus
Requires-Dist: requests>=2.0; extra == "plus"
Requires-Dist: aiohttp>=3.8; extra == "plus"
Requires-Dist: websockets>=10.0; extra == "plus"
Provides-Extra: http
Requires-Dist: requests>=2.0; extra == "http"
Requires-Dist: aiohttp>=3.8; extra == "http"
Provides-Extra: ws
Requires-Dist: websockets>=10.0; extra == "ws"
Dynamic: license-file
